atlassian_jwt_auth/__init__.py
atlassian_jwt_auth/algorithms.py
atlassian_jwt_auth/auth.py
atlassian_jwt_auth/exceptions.py
atlassian_jwt_auth/key.py
atlassian_jwt_auth/py.typed
atlassian_jwt_auth/signer.py
atlassian_jwt_auth/verifier.py
atlassian_jwt_auth/contrib/README.md
atlassian_jwt_auth/contrib/__init__.py
atlassian_jwt_auth/contrib/requests.py
atlassian_jwt_auth/contrib/aiohttp/__init__.py
atlassian_jwt_auth/contrib/aiohttp/auth.py
atlassian_jwt_auth/contrib/aiohttp/key.py
atlassian_jwt_auth/contrib/aiohttp/verifier.py
atlassian_jwt_auth/contrib/django/__init__.py
atlassian_jwt_auth/contrib/django/decorators.py
atlassian_jwt_auth/contrib/django/middleware.py
atlassian_jwt_auth/contrib/flask_app/__init__.py
atlassian_jwt_auth/contrib/flask_app/decorators.py
atlassian_jwt_auth/contrib/server/__init__.py
atlassian_jwt_auth/contrib/tests/__init__.py
atlassian_jwt_auth/contrib/tests/test_requests.py
atlassian_jwt_auth/contrib/tests/utils.py
atlassian_jwt_auth/contrib/tests/aiohttp/__init__.py
atlassian_jwt_auth/contrib/tests/aiohttp/test_auth.py
atlassian_jwt_auth/contrib/tests/aiohttp/test_public_key_provider.py
atlassian_jwt_auth/contrib/tests/aiohttp/test_verifier.py
atlassian_jwt_auth/frameworks/__init__.py
atlassian_jwt_auth/frameworks/common/__init__.py
atlassian_jwt_auth/frameworks/common/asap.py
atlassian_jwt_auth/frameworks/common/backend.py
atlassian_jwt_auth/frameworks/common/decorators.py
atlassian_jwt_auth/frameworks/common/utils.py
atlassian_jwt_auth/frameworks/common/tests/__init__.py
atlassian_jwt_auth/frameworks/common/tests/test_decorators.py
atlassian_jwt_auth/frameworks/common/tests/test_utils.py
atlassian_jwt_auth/frameworks/django/__init__.py
atlassian_jwt_auth/frameworks/django/backend.py
atlassian_jwt_auth/frameworks/django/decorators.py
atlassian_jwt_auth/frameworks/django/middleware.py
atlassian_jwt_auth/frameworks/django/tests/__init__.py
atlassian_jwt_auth/frameworks/django/tests/settings.py
atlassian_jwt_auth-21.0.0.dist-info/licenses/AUTHORS
atlassian_jwt_auth-21.0.0.dist-info/licenses/LICENSE
atlassian_jwt_auth-21.0.0.dist-info/METADATA
atlassian_jwt_auth-21.0.0.dist-info/WHEEL
atlassian_jwt_auth-21.0.0.dist-info/pbr.json
atlassian_jwt_auth-21.0.0.dist-info/top_level.txt
atlassian_jwt_auth-21.0.0.dist-info/RECORD
