Metadata-Version: 2.4
Name: atlassian-jwt-auth
Version: 21.0.0
Summary: Python implementation of the Atlassian Service to Service Authentication specification.
Home-page: https://github.com/atlassian/asap-authentication-python
Author: Atlassian
Author-email: dblack@atlassian.com
License: MIT
Project-URL: Bug Tracker, https://github.com/atlassian/asap-authentication-python/issues
Project-URL: Source Code, https://github.com/atlassian/asap-authentication-python
Platform: any
Classifier: Development Status :: 4 - Beta
Classifier: Environment :: Console
Classifier: Intended Audience :: Developers
Classifier: Operating System :: OS Independent
Classifier: Programming Language :: Python
Classifier: Programming Language :: Python :: 3
Classifier: Programming Language :: Python :: 3.9
Classifier: Programming Language :: Python :: 3.10
Classifier: Programming Language :: Python :: 3.11
Classifier: Programming Language :: Python :: 3.12
Classifier: Programming Language :: Python :: 3.13
Classifier: License :: OSI Approved :: MIT License
License-File: LICENSE
License-File: AUTHORS
Requires-Dist: PyJWT<3.0.0,>=2.4.0
Requires-Dist: PyJWT[crypto]<3.0.0,>=2.4.0
Requires-Dist: requests<3.0.0,>=2.8.1
Requires-Dist: CacheControl
Dynamic: author
Dynamic: author-email
Dynamic: classifier
Dynamic: description
Dynamic: license
Dynamic: license-file
Dynamic: platform
Dynamic: project-url
Dynamic: requires-dist
Dynamic: summary
